pyqt_search_bar/__init__.py
pyqt_search_bar/searchBar.py
pyqt_search_bar/ico/__init__.py
pyqt_search_bar/ico/close.svg
pyqt_search_bar/ico/search.svg
pyqt_search_bar/style/__init__.py
pyqt_search_bar/style/lineedit.css
pyqt_search_bar/style/search_bar.css
pyqt_search_bar/style/widget.css
pyqt_search_bar-0.0.14.dist-info/LICENSE
pyqt_search_bar-0.0.14.dist-info/METADATA
pyqt_search_bar-0.0.14.dist-info/WHEEL
pyqt_search_bar-0.0.14.dist-info/top_level.txt
pyqt_search_bar-0.0.14.dist-info/RECORD
