Metadata-Version: 2.1
Name: pyqt-search-bar
Version: 0.0.14
Summary: PyQt search bar
Home-page: https://github.com/yjg30737/pyqt-search-bar.git
Author: Jung Gyu Yoon
Author-email: yjg30737@gmail.com
License: MIT
License-File: LICENSE
Requires-Dist: PyQt5 (>=5.8)
Requires-Dist: pyqt-resource-helper (>=0.0.1)
Requires-Dist: pyqt-svg-button (>=0.0.1)
